{"__symbolic":"module","version":4,"metadata":{"platformWorkerAppDynamic":{"__symbolic":"call","expression":{"__symbolic":"reference","module":"@angular/core","name":"createPlatformFactory","line":22,"character":4},"arguments":[{"__symbolic":"reference","module":"@angular/platform-browser-dynamic","name":"ɵplatformCoreDynamic","line":22,"character":26},"workerAppDynamic",[{"provide":{"__symbolic":"reference","module":"@angular/core","name":"COMPILER_OPTIONS","line":24,"character":17},"useValue":{"providers":[{"provide":{"__symbolic":"reference","module":"@angular/compiler","name":"ResourceLoader","line":25,"character":41},"useClass":{"__symbolic":"reference","module":"@angular/platform-browser-dynamic","name":"ɵResourceLoaderImpl","line":25,"character":67},"deps":[]}]},"multi":true},{"provide":{"__symbolic":"reference","module":"@angular/core","name":"PLATFORM_ID","line":28,"character":16},"useValue":{"__symbolic":"reference","module":"@angular/common","name":"ɵPLATFORM_WORKER_UI_ID","line":28,"character":39}}]]},"VERSION":{"__symbolic":"new","expression":{"__symbolic":"reference","module":"@angular/core","name":"Version","line":21,"character":27},"arguments":["10.0.0-rc.0+259.sha-ce879fc"]}},"origins":{"platformWorkerAppDynamic":"./platform-webworker-dynamic","VERSION":"./platform-webworker-dynamic"},"importAs":"@angular/platform-webworker-dynamic"}